metatree/__init__.py
metatree/__main__.py
metatree/common.py
metatree/exception.py
metatree/f_measure_tree.py
metatree/logger.py
metatree/mismatch_table.py
metatree/pipeline.py
metatree/tree_decorate.py
metatree/tree_dist.py
metatree/tree_root.py
metatree/external/__init__.py
metatree/external/tree_compare.py
metatree/io/__init__.py
metatree/io/batchfile.py
metatree/io/rf_results.py
metatree/io/taxonomy_file.py
metatree-0.0.1.data/data/LICENSE
metatree-0.0.1.dist-info/LICENSE
metatree-0.0.1.dist-info/METADATA
metatree-0.0.1.dist-info/WHEEL
metatree-0.0.1.dist-info/entry_points.txt
metatree-0.0.1.dist-info/top_level.txt
metatree-0.0.1.dist-info/RECORD
